README.md
setup.py
flask_rabmq/__init__.py
flask_rabmq/consumer_producer.py
flask_rabmq/exceptions.py
flask_rabmq/rabbitmq.py
flask_rabmq/utils.py
flask_rabmq.egg-info/PKG-INFO
flask_rabmq.egg-info/SOURCES.txt
flask_rabmq.egg-info/dependency_links.txt
flask_rabmq.egg-info/requires.txt
flask_rabmq.egg-info/top_level.txt
flask_rabmq.egg-info/zip-safe