Metadata-Version: 2.1
Name: flask-rabmq
Version: 0.0.23
Summary: Adds Rabbitmq support to your Flask application.
Home-page: https://github.com/flask-rabmq/flask-rabmq
Author: chenxiaolong
Author-email: cxiaolong6@gmail.com
License: MIT
Keywords: python flask Rabbitmq
Platform: UNKNOWN
Classifier: License :: OSI Approved :: MIT License
Classifier: Programming Language :: Python
Classifier: Intended Audience :: Developers
Classifier: Operating System :: OS Independent
Requires-Python: >=2.7, !=3.0.*, !=3.1.*, !=3.2.*, !=3.3.*, !=3.4.*, !=3.5.*
